openpd/__init__.py
openpd/ensemble.py
openpd/forceEncoder.py
openpd/runTest.py
openpd/simulation.py
openpd/__pycache__/__init__.cpython-37.pyc
openpd/core/__init__.py
openpd/core/atom.py
openpd/core/chain.py
openpd/core/peptide.py
openpd/core/system.py
openpd/core/topology.py
openpd/data/__init__.py
openpd/data/pdff/nonbonded/ASN-ASN.npy
openpd/data/pdff/nonbonded/ASN-ASP.npy
openpd/data/pdff/nonbonded/ASN-GLN.npy
openpd/data/pdff/nonbonded/ASN-GLY.npy
openpd/data/pdff/nonbonded/ASN-ILE.npy
openpd/data/pdff/nonbonded/ASN-LEU.npy
openpd/data/pdff/nonbonded/ASN-LYS.npy
openpd/data/pdff/nonbonded/ASN-TRP.npy
openpd/data/pdff/nonbonded/ASN-TYR.npy
openpd/data/pdff/nonbonded/LEU-ASP.npy
openpd/data/pdff/nonbonded/LEU-GLN.npy
openpd/data/pdff/nonbonded/LEU-ILE.npy
openpd/data/pdff/nonbonded/LEU-LEU.npy
openpd/data/pdff/nonbonded/LEU-LYS.npy
openpd/data/pdff/nonbonded/LEU-TRP.npy
openpd/data/pdff/nonbonded/LEU-TYR.npy
openpd/data/pdff/nonbonded/TYR-GLN.npy
openpd/data/pdff/nonbonded/TYR-TYR.npy
openpd/data/pdff/nonbonded/coord.npy
openpd/data/pdff/torsion/ASN-ASP.npy
openpd/data/pdff/torsion/ASN-GLN.npy
openpd/data/pdff/torsion/ASN-GLY.npy
openpd/data/pdff/torsion/ASN-ILE.npy
openpd/data/pdff/torsion/ASN-LEU.npy
openpd/data/pdff/torsion/ASN-LYS.npy
openpd/data/pdff/torsion/ASN-TRP.npy
openpd/data/pdff/torsion/ASN-TYR.npy
openpd/data/pdff/torsion/LEU-ASP.npy
openpd/data/pdff/torsion/LEU-GLN.npy
openpd/data/pdff/torsion/LEU-ILE.npy
openpd/data/pdff/torsion/LEU-LEU.npy
openpd/data/pdff/torsion/LEU-LYS.npy
openpd/data/pdff/torsion/LEU-TRP.npy
openpd/data/pdff/torsion/LEU-TYR.npy
openpd/data/pdff/torsion/TYR-GLN.npy
openpd/data/pdff/torsion/coord.npy
openpd/data/template/ALA.json
openpd/data/template/ARG.json
openpd/data/template/ASN.json
openpd/data/template/ASP.json
openpd/data/template/GLN.json
openpd/data/template/GLY.json
openpd/data/template/ILE.json
openpd/data/template/LEU.json
openpd/data/template/LYS.json
openpd/data/template/PRO.json
openpd/data/template/SER.json
openpd-0.2.5.dist-info/LICENSE
openpd-0.2.5.dist-info/METADATA
openpd-0.2.5.dist-info/WHEEL
openpd-0.2.5.dist-info/top_level.txt
openpd-0.2.5.dist-info/RECORD
