Metadata-Version: 2.1
Name: openpd
Version: 0.2.5
Summary: OpenPD, standing for Open Peptide Dynamics, is a python package for peptide dynamics simulation
Home-page: https://openpd.net/en/latest/
Author: Zhenyu Wei
Author-email: zhenyuwei99@gmail.com
License: UNKNOWN
Project-URL: Documentation, https://openpd.net/en/latest/
Project-URL: Source Code, https://github.com/zhenyuwei99/openpd
Keywords: Peptide dynamics simulation package
Platform: UNKNOWN
Classifier: Development Status :: 3 - Alpha
Classifier: Topic :: Scientific/Engineering :: Bio-Informatics
Classifier: Topic :: Scientific/Engineering :: Physics
Classifier: Topic :: Scientific/Engineering :: Chemistry
Classifier: License :: OSI Approved :: GNU General Public License v3 (GPLv3)
Classifier: Programming Language :: Python :: 3.7
Classifier: Programming Language :: Python :: 3.8
Classifier: Programming Language :: Python :: 3.9
Requires-Python: >=3.7
Requires-Dist: numpy
Requires-Dist: matplotlib
Requires-Dist: pytest
Requires-Dist: scipy
